odoo10_addon_report_qweb_parameter-10.0.1.0.1-py2.7-nspkg.pth
odoo/addons/report_qweb_parameter/README.rst
odoo/addons/report_qweb_parameter/__init__.py
odoo/addons/report_qweb_parameter/__manifest__.py
odoo/addons/report_qweb_parameter/demo/test_report_field_length.xml
odoo/addons/report_qweb_parameter/models/__init__.py
odoo/addons/report_qweb_parameter/models/ir_qweb.py
odoo/addons/report_qweb_parameter/static/description/icon.png
odoo/addons/report_qweb_parameter/tests/__init__.py
odoo/addons/report_qweb_parameter/tests/test_report_qweb_parameter.py
odoo10_addon_report_qweb_parameter-10.0.1.0.1.dist-info/DESCRIPTION.rst
odoo10_addon_report_qweb_parameter-10.0.1.0.1.dist-info/METADATA
odoo10_addon_report_qweb_parameter-10.0.1.0.1.dist-info/RECORD
odoo10_addon_report_qweb_parameter-10.0.1.0.1.dist-info/WHEEL
odoo10_addon_report_qweb_parameter-10.0.1.0.1.dist-info/metadata.json
odoo10_addon_report_qweb_parameter-10.0.1.0.1.dist-info/namespace_packages.txt
odoo10_addon_report_qweb_parameter-10.0.1.0.1.dist-info/top_level.txt
