Metadata-Version: 2.0
Name: odoo10-addon-report-qweb-parameter
Version: 10.0.1.0.1
Summary: Add new parameters for qweb templates in order to reduce field length
Home-page: https://github.com/oca/reporting-engine
Author: Creu Blanca,Odoo Community Association (OCA)
Author-email: support@odoo-community.org
License: AGPL-3
Platform: UNKNOWN
Classifier: Programming Language :: Python :: 2.7
Classifier: Framework :: Odoo
Classifier: License :: OSI Approved :: GNU Affero General Public License v3
Requires-Dist: odoo (<10.1dev,>=10.0)
